pivimage/__init__.py
pivimage/_version.py
pivimage/file_wrapper.py
pivimage/meta.py
pivimage/pivimage.py
tests/__init__.py
tests/test_meta.py
tests/test_pivimage.py
tests/test_pivimagepair.py
tests/test_pivimages.py
tests/test_version.py
pivimage-0.7.3.dist-info/LICENSE
pivimage-0.7.3.dist-info/METADATA
pivimage-0.7.3.dist-info/WHEEL
pivimage-0.7.3.dist-info/top_level.txt
pivimage-0.7.3.dist-info/RECORD
