Metadata-Version: 2.1
Name: pivimage
Version: 0.7.3
Summary: Small library reading images and providing PIV-specific utilities.
Home-page: https://github.com/matthiasprobst/pivimage
Author: Matthias Probst
Author-email: matthias.probst@kit.edu
Classifier: Programming Language :: Python :: 3
Classifier: Programming Language :: Python :: 3.8
Classifier: Programming Language :: Python :: 3.9
Classifier: Programming Language :: Python :: 3.10
Classifier: Programming Language :: Python :: 3.11
Classifier: Programming Language :: Python :: 3.12
Classifier: Programming Language :: Python :: 3.13
Classifier: License :: OSI Approved :: MIT License
Classifier: Operating System :: OS Independent
Classifier: Development Status :: 4 - Beta
Requires-Python: >=3.8
License-File: LICENSE
Requires-Dist: appdirs>=1.4.4
Requires-Dist: numpy
Requires-Dist: pco-tools>=1.0.0
Requires-Dist: opencv-python>=4.5.3.56
Requires-Dist: importlib-metadata>=5.0.0
Requires-Dist: matplotlib
Provides-Extra: complete
Requires-Dist: pivtestdata>=0.4.0; extra == "complete"
Requires-Dist: pytest>=7.1.2; extra == "complete"
Requires-Dist: pytest-cov; extra == "complete"
Requires-Dist: xarray; extra == "complete"
Provides-Extra: test
Requires-Dist: pivtestdata>=0.4.0; extra == "test"
Requires-Dist: pytest>=7.1.2; extra == "test"
Requires-Dist: pytest-cov; extra == "test"
Requires-Dist: xarray; extra == "test"
